<Feature version="2">
    <Feature1 src="C:\GIT\private-github\hello-world\feature1.txt">This is the first feature, made a minor bugfix.</Feature1>
    <Feature2 src="C:\GIT\private-github\hello-world\feature2.txt" version="2">This is the second feature</Feature2>
    <Feature3 src="C:\GIT\private-github\hello-world\feature3.txt">This is the third feature</Feature3>
    <Feature4 src="C:\GIT\private-github\hello-world\feature4.txt">New super feature</Feature4>
    <Feature5 src="C:\GIT\private-github\hello-world\feature5.txt">Smart feature</Feature5>
    <Feature6 src="C:\GIT\private-github\Hello-World\feature6.txt">Feature no 6</Feature6>
</Feature>